[
  {
    "movieName": "Avatar",
    "directorName": "James Cameron",
    "releaseDate": "18 Dec 2009",
    "Summary": "Tan people want to be blue people in magical forest",
    "viewCount":"0"
  },
  {
    "movieName": "Blood Diamond",
    "directorName": "Edward Zwick",
    "releaseDate": "08 Dec 2006",
    "Summary": "White man wants to make money with diamonds",
    "viewCount":"0"
  },
  {
    "movieName": "The Prestige",
    "directorName": "Christopher Nolan",
    "releaseDate": "20 Oct 2006",
    "Summary": "Two bois wanna be the best magic man",
    "viewCount":"0"
  },
  {
    "movieName": "Inception",
    "directorName": "Christopher Nolan",
    "releaseDate": "16 Jul 2010",
    "Summary": "Getting in someone's head in their head's head",
    "viewCount":"0"
  }
]
